monad_std/__init__.py
monad_std/either.py
monad_std/error.py
monad_std/iter/__init__.py
monad_std/iter/impl/__init__.py
monad_std/iter/impl/array_chunk.py
monad_std/iter/impl/batch.py
monad_std/iter/impl/chain.py
monad_std/iter/impl/chunk.py
monad_std/iter/impl/default_iter.py
monad_std/iter/impl/enumerate.py
monad_std/iter/impl/filter.py
monad_std/iter/impl/filter_map.py
monad_std/iter/impl/flat_map.py
monad_std/iter/impl/flatten.py
monad_std/iter/impl/fuse.py
monad_std/iter/impl/group.py
monad_std/iter/impl/inspect.py
monad_std/iter/impl/intersperse.py
monad_std/iter/impl/map.py
monad_std/iter/impl/once.py
monad_std/iter/impl/partition.py
monad_std/iter/impl/peekable.py
monad_std/iter/impl/repeat.py
monad_std/iter/impl/scan.py
monad_std/iter/impl/skip.py
monad_std/iter/impl/take.py
monad_std/iter/impl/unique.py
monad_std/iter/impl/zip.py
monad_std/iter/iter.py
monad_std/option.py
monad_std/prelude/__init__.py
monad_std/result.py
monad_std/std_types/__init__.py
monad_std/std_types/pydict.py
monad_std/std_types/pydict.pyi
monad_std/std_types/pylist.py
monad_std/std_types/pylist.pyi
monad_std/std_types/pyset.py
monad_std/std_types/pyset.pyi
monad_std/std_types/pytuple.py
monad_std/std_types/pytuple.pyi
monad_std/typedef/__init__.py
monad_std/typedef/cmp.py
monad_std/typedef/ops.py
monad_std/utils/__init__.py
monad_std/utils/cmp.py
monad_std-0.10.0.dist-info/LICENSE-APACHE
monad_std-0.10.0.dist-info/LICENSE-MIT
monad_std-0.10.0.dist-info/METADATA
monad_std-0.10.0.dist-info/WHEEL
monad_std-0.10.0.dist-info/RECORD
