Metadata-Version: 2.1
Name: monad-std
Version: 0.10.0
Summary: A library of rust-styled monad utils for python.
Home-page: https://embers-of-the-fire.github.io/monad-std/
License: MIT OR Apache-2.0
Keywords: monad,functional,rust,pure-python,fp
Author: Embers-of-the-Fire
Author-email: stellarishs@163.com
Requires-Python: >=3.8,<4.0
Classifier: Development Status :: 4 - Beta
Classifier: Intended Audience :: Developers
Classifier: Intended Audience :: Science/Research
Classifier: License :: OSI Approved :: Apache Software License
Classifier: License :: OSI Approved :: MIT License
Classifier: License :: Other/Proprietary License
Classifier: Programming Language :: Python :: 3
Classifier: Programming Language :: Python :: 3.8
Classifier: Programming Language :: Python :: 3.9
Classifier: Programming Language :: Python :: 3.10
Classifier: Programming Language :: Python :: 3.11
Classifier: Programming Language :: Python :: 3.12
Classifier: Programming Language :: Python :: 3 :: Only
Classifier: Programming Language :: Rust
Classifier: Topic :: Software Development :: Libraries
Classifier: Topic :: Software Development :: Libraries :: Python Modules
Classifier: Topic :: Utilities
Classifier: Typing :: Typed
Requires-Dist: pytest (>=8.0.0,<9.0.0)
Project-URL: Repository, https://github.com/Embers-of-the-Fire/monad-std
